kosimpletax/__init__.py
kosimpletax/y2018/__init__.py
kosimpletax/y2018/formula.py
kosimpletax/y2018/tax_calculator.py
kosimpletax-1.0.dist-info/LICENSE
kosimpletax-1.0.dist-info/METADATA
kosimpletax-1.0.dist-info/WHEEL
kosimpletax-1.0.dist-info/top_level.txt
kosimpletax-1.0.dist-info/RECORD
